{
  "2012(2011)_Amnesty_International.pdf": [
    {
      "name": "Afghanistan",
      "report_page": 55
    },
    {
      "name": "Albania",
      "report_page": 58
    },
    {
      "name": "Algeria",
      "report_page": 60
    },
    {
      "name": "Angola",
      "report_page": 62
    },
    {
      "name": "Argentina",
      "report_page": 65
    },
    {
      "name": "Armenia",
      "report_page": 66
    },
    {
      "name": "Australia",
      "report_page": 67
    },
    {
      "name": "Austria",
      "report_page": 68
    },
    {
      "name": "Azerbaijan",
      "report_page": 69
    },
    {
      "name": "Bahamas",
      "report_page": 71
    },
    {
      "name": "Bahrain",
      "report_page": 72
    },
    {
      "name": "Bangladesh",
      "report_page": 75
    },
    {
      "name": "Belarus",
      "report_page": 77
    },
    {
      "name": "Belgium",
      "report_page": 79
    },
    {
      "name": "Benin",
      "report_page": 81
    },
    {
      "name": "Bolivia",
      "report_page": 81
    },
    {
      "name": "Bosnia and Herzegovina",
      "report_page": 82
    },
    {
      "name": "Brazil",
      "report_page": 86
    },
    {
      "name": "Bulgaria",
      "report_page": 90
    },
    {
      "name": "Burkina Faso",
      "report_page": 91
    },
    {
      "name": "Burundi",
      "report_page": 92
    },
    {
      "name": "Cambodia",
      "report_page": 95
    },
    {
      "name": "Cameroon",
      "report_page": 97
    },
    {
      "name": "Canada",
      "report_page": 99
    },
    {
      "name": "Central African Republic",
      "report_page": 101
    },
    {
      "name": "Chad",
      "report_page": 103
    },
    {
      "name": "Chile",
      "report_page": 105
    },
    {
      "name": "China",
      "report_page": 107
    },
    {
      "name": "Colombia",
      "report_page": 111
    },
    {
      "name": "Congo (Republic of)",
      "report_page": 115
    },
    {
      "name": "Côte d'Ivoire",
      "report_page": 116
    },
    {
      "name": "Croatia",
      "report_page": 119
    },
    {
      "name": "Cuba",
      "report_page": 121
    },
    {
      "name": "Cyprus",
      "report_page": 123
    },
    {
      "name": "Czech Republic",
      "report_page": 124
    },
    {
      "name": "Democratic Republic of the Congo",
      "report_page": 126
    },
    {
      "name": "Denmark",
      "report_page": 130
    },
    {
      "name": "Dominican Republic",
      "report_page": 131
    },
    {
      "name": "Ecuador",
      "report_page": 133
    },
    {
      "name": "Egypt",
      "report_page": 134
    },
    {
      "name": "El Salvador",
      "report_page": 139
    },
    {
      "name": "Equatorial Guinea",
      "report_page": 140
    },
    {
      "name": "Eritrea",
      "report_page": 142
    },
    {
      "name": "Ethiopia",
      "report_page": 144
    },
    {
      "name": "Fiji",
      "report_page": 147
    },
    {
      "name": "Finland",
      "report_page": 148
    },
    {
      "name": "France",
      "report_page": 149
    },
    {
      "name": "Gambia",
      "report_page": 152
    },
    {
      "name": "Georgia",
      "report_page": 153
    },
    {
      "name": "Germany",
      "report_page": 155
    },
    {
      "name": "Ghana",
      "report_page": 156
    },
    {
      "name": "Greece",
      "report_page": 157
    },
    {
      "name": "Guatemala",
      "report_page": 160
    },
    {
      "name": "Guinea",
      "report_page": 162
    },
    {
      "name": "Guinea-Bissau",
      "report_page": 163
    },
    {
      "name": "Guyana",
      "report_page": 165
    },
    {
      "name": "Haiti",
      "report_page": 166
    },
    {
      "name": "Honduras",
      "report_page": 168
    },
    {
      "name": "Hungary",
      "report_page": 169
    },
    {
      "name": "India",
      "report_page": 171
    },
    {
      "name": "Indonesia",
      "report_page": 175
    },
    {
      "name": "Iran",
      "report_page": 177
    },
    {
      "name": "Iraq",
      "report_page": 181
    },
    {
      "name": "Ireland",
      "report_page": 184
    },
    {
      "name": "Israel and the Occupied Palestinian Territories",
      "report_page": 186
    },
    {
      "name": "Italy",
      "report_page": 190
    },
    {
      "name": "Jamaica",
      "report_page": 193
    },
    {
      "name": "Japan",
      "report_page": 195
    },
    {
      "name": "Jordan",
      "report_page": 196
    },
    {
      "name": "Kazakhstan",
      "report_page": 198
    },
    {
      "name": "Kenya",
      "report_page": 201
    },
    {
      "name": "Korea (Democratic People's Republic of)",
      "report_page": 204
    },
    {
      "name": "Korea (Republic of)",
      "report_page": 206
    },
    {
      "name": "Kuwait",
      "report_page": 207
    },
    {
      "name": "Kyrgyzstan",
      "report_page": 209
    },
    {
      "name": "Laos",
      "report_page": 211
    },
    {
      "name": "Lebanon",
      "report_page": 212
    },
    {
      "name": "Liberia",
      "report_page": 214
    },
    {
      "name": "Libya",
      "report_page": 217
    },
    {
      "name": "Lithuania",
      "report_page": 222
    },
    {
      "name": "Macedonia",
      "report_page": 222
    },
    {
      "name": "Madagascar",
      "report_page": 224
    },
    {
      "name": "Malawi",
      "report_page": 226
    },
    {
      "name": "Malaysia",
      "report_page": 227
    },
    {
      "name": "Maldives",
      "report_page": 229
    },
    {
      "name": "Mali",
      "report_page": 230
    },
    {
      "name": "Malta",
      "report_page": 231
    },
    {
      "name": "Mauritania",
      "report_page": 232
    },
    {
      "name": "Mexico",
      "report_page": 234
    },
    {
      "name": "Moldova",
      "report_page": 238
    },
    {
      "name": "Mongolia",
      "report_page": 239
    },
    {
      "name": "Montenegro",
      "report_page": 240
    },
    {
      "name": "Morocco/Western Sahara",
      "report_page": 242
    },
    {
      "name": "Mozambique",
      "report_page": 244
    },
    {
      "name": "Myanmar",
      "report_page": 246
    },
    {
      "name": "Namibia",
      "report_page": 249
    },
    {
      "name": "Nepal",
      "report_page": 250
    },
    {
      "name": "Netherlands",
      "report_page": 252
    },
    {
      "name": "New Zealand",
      "report_page": 253
    },
    {
      "name": "Nicaragua",
      "report_page": 254
    },
    {
      "name": "Niger",
      "report_page": 255
    },
    {
      "name": "Nigeria",
      "report_page": 256
    },
    {
      "name": "Norway",
      "report_page": 260
    },
    {
      "name": "Oman",
      "report_page": 261
    },
    {
      "name": "Pakistan",
      "report_page": 262
    },
    {
      "name": "Palestinian Authority",
      "report_page": 265
    },
    {
      "name": "Panama",
      "report_page": 268
    },
    {
      "name": "Paraguay",
      "report_page": 269
    },
    {
      "name": "Peru",
      "report_page": 270
    },
    {
      "name": "Philippines",
      "report_page": 272
    },
    {
      "name": "Poland",
      "report_page": 274
    },
    {
      "name": "Portugal",
      "report_page": 275
    },
    {
      "name": "Puerto Rico",
      "report_page": 276
    },
    {
      "name": "Qatar",
      "report_page": 277
    },
    {
      "name": "Romania",
      "report_page": 278
    },
    {
      "name": "Russian Federation",
      "report_page": 280
    },
    {
      "name": "Rwanda",
      "report_page": 284
    },
    {
      "name": "Saudi Arabia",
      "report_page": 286
    },
    {
      "name": "Senegal",
      "report_page": 290
    },
    {
      "name": "Serbia",
      "report_page": 291
    },
    {
      "name": "Sierra Leone",
      "report_page": 295
    },
    {
      "name": "Singapore",
      "report_page": 298
    },
    {
      "name": "Slovakia",
      "report_page": 299
    },
    {
      "name": "Slovenia",
      "report_page": 301
    },
    {
      "name": "Somalia",
      "report_page": 302
    },
    {
      "name": "South Africa",
      "report_page": 305
    },
    {
      "name": "South Sudan",
      "report_page": 309
    },
    {
      "name": "Spain",
      "report_page": 311
    },
    {
      "name": "Sri Lanka",
      "report_page": 314
    },
    {
      "name": "Sudan",
      "report_page": 316
    },
    {
      "name": "Swaziland",
      "report_page": 320
    },
    {
      "name": "Sweden",
      "report_page": 322
    },
    {
      "name": "Switzerland",
      "report_page": 323
    },
    {
      "name": "Syria",
      "report_page": 324
    },
    {
      "name": "Taiwan",
      "report_page": 329
    },
    {
      "name": "Tajikistan",
      "report_page": 330
    },
    {
      "name": "Tanzania",
      "report_page": 331
    },
    {
      "name": "Thailand",
      "report_page": 332
    },
    {
      "name": "Timor-Leste",
      "report_page": 335
    },
    {
      "name": "Togo",
      "report_page": 336
    },
    {
      "name": "Trinidad and Tobago",
      "report_page": 337
    },
    {
      "name": "Tunisia",
      "report_page": 338
    },
    {
      "name": "Turkey",
      "report_page": 341
    },
    {
      "name": "Turkmenistan",
      "report_page": 345
    },
    {
      "name": "Uganda",
      "report_page": 346
    },
    {
      "name": "Ukraine",
      "report_page": 349
    },
    {
      "name": "United Arab Emirates",
      "report_page": 351
    },
    {
      "name": "United Kingdom",
      "report_page": 352
    },
    {
      "name": "United States of America",
      "report_page": 356
    },
    {
      "name": "Uruguay",
      "report_page": 360
    },
    {
      "name": "Uzbekistan",
      "report_page": 361
    },
    {
      "name": "Venezuela",
      "report_page": 363
    },
    {
      "name": "Viet Nam",
      "report_page": 365
    },
    {
      "name": "Yemen",
      "report_page": 367
    },
    {
      "name": "Zimbabwe",
      "report_page": 371
    }
  ]
}